django_counter_cache_fuxy/__init__.py
django_counter_cache_fuxy/counter.py
django_counter_cache_fuxy/fields.py
django_counter_cache_fuxy/management/__init__.py
django_counter_cache_fuxy/management/commands/__init__.py
django_counter_cache_fuxy/management/commands/list_counters.py
django_counter_cache_fuxy/management/commands/rebuild_counter.py
docs/__init__.py
docs/source/__init__.py
docs/source/conf.py
django_counter_cache_fuxy-0.1.3.dist-info/LICENSE
django_counter_cache_fuxy-0.1.3.dist-info/METADATA
django_counter_cache_fuxy-0.1.3.dist-info/WHEEL
django_counter_cache_fuxy-0.1.3.dist-info/top_level.txt
django_counter_cache_fuxy-0.1.3.dist-info/RECORD
