Metadata-Version: 2.1
Name: django-counter-cache-fuxy
Version: 0.1.3
Summary: ddjango-counter-cache-fuxy makes it extremely easy to denormalize and keep track of related model counts.
Home-page: https://github.com/fukszssl247/django-counter-cache-field
Author: Hat Dao
Author-email: enjoy3013@gmail.com
License: MIT License
Classifier: Environment :: Web Environment
Classifier: Framework :: Django
Classifier: Intended Audience :: Developers
Classifier: License :: OSI Approved :: MIT License
Classifier: Operating System :: OS Independent
Classifier: Programming Language :: Python
Classifier: Programming Language :: Python :: 3
Classifier: Programming Language :: Python :: 3.6
Classifier: Programming Language :: Python :: 3.7
Classifier: Programming Language :: Python :: 3.8
Classifier: Topic :: Internet :: WWW/HTTP
Classifier: Topic :: Internet :: WWW/HTTP :: Dynamic Content
License-File: LICENSE
Provides-Extra: test
Requires-Dist: django ; extra == 'test'
